{
  "welcomeMessage": "Bienvenue dans l'EMR de Hôpital Saint-Nicolas",
  "site": "HSN_SAINT_MARC",
  "dossierIdentifierPrefix": "HSN",

  "components": [
    "clinicianDashboard",
    "visitNote",
    "allergies",
    "patientRegistration",
    "visitManagement",
    "checkIn",
    "checkInHomepageApp",
    "systemAdministration",
    "myAccount",
    "waitingForConsult",
    "overviewReports",
    "dataExports",
    "monitoringReports",
    "todaysVisits",
    "relationships",
    "programs",
    "exportPatients",
    "importPatients",
    "vitals",
    "mentalHealth",
    "covid19",
    "edTriage",
    "edTriageQueue"
	],

  "globalProperties": {
    "coreapps.defaultPatientIdentifierLocation": "97c241a0-eaec-11e5-a837-0800200c9a66"
  },

  "dispositionConfig": "file:configuration/pih/pih-dispositions-haiti-inpatient.json"
}
